GestureProj/Readme.txt
GestureProj/__init__.py
GestureProj/gestures.png
GestureProj/main.py
GestureProj/remover.py
GestureProj/rootfold/cvfeed.py
GestureProj/rootfold/data_capture.py
GestureProj/rootfold/global_main.py
GestureProj/rootfold/log.csv
GestureProj/rootfold/model_lowres.keras
GestureProj/rootfold/remover__.py
GestureProj/rootfold/trainer.py
GestureProj/rootfold/0/1705671141.185683.png
GestureProj/rootfold/1/1705671146.8658345.png
GestureProj/rootfold/2/1705671152.425987.png
GestureProj/rootfold/3/1705671155.2654438.png
GestureProj/rootfold/4/1705671157.9895782.png
GestureProj/rootfold/5/1705671161.401656.png
gestureproj-1.0.7.dist-info/METADATA
gestureproj-1.0.7.dist-info/WHEEL
gestureproj-1.0.7.dist-info/entry_points.txt
gestureproj-1.0.7.dist-info/licenses/LICENSE
gestureproj-1.0.7.dist-info/RECORD
